neon_solver_ddg_plugin/__init__.py
neon_solver_ddg_plugin-0.0.2a1.dist-info/METADATA
neon_solver_ddg_plugin-0.0.2a1.dist-info/WHEEL
neon_solver_ddg_plugin-0.0.2a1.dist-info/entry_points.txt
neon_solver_ddg_plugin-0.0.2a1.dist-info/top_level.txt
neon_solver_ddg_plugin-0.0.2a1.dist-info/zip-safe
neon_solver_ddg_plugin-0.0.2a1.dist-info/RECORD
