Metadata-Version: 2.1
Name: neon-solver-ddg-plugin
Version: 0.0.2a1
Summary: A question solver plugin for ovos/neon/mycroft
Home-page: https://github.com/NeonGeckoCom/neon_solver_ddg_plugin
Author: Neongecko
Author-email: developers@neon.ai
License: bsd3
Keywords: mycroft plugin utterance fallback query
Platform: UNKNOWN
Requires-Dist: simplematch
Requires-Dist: requests
Requires-Dist: requests-cache
Requires-Dist: neon-solvers (>=0.0.2a1,~=0.0)
